torchhacks/__init__.py
torchhacks/lazyload.py
torchhacks-0.0.1.dist-info/LICENSE
torchhacks-0.0.1.dist-info/METADATA
torchhacks-0.0.1.dist-info/WHEEL
torchhacks-0.0.1.dist-info/top_level.txt
torchhacks-0.0.1.dist-info/RECORD
