Metadata-Version: 2.1
Name: torchhacks
Version: 0.0.1
Summary: Hacks for PyTorch
Home-page: https://lernappar.at/torchhacks
Author: Thomas Viehmann, MathInf GmbH
License-File: LICENSE
Requires-Dist: torch
